cloudcoil/models/cert_manager/__init__.py
cloudcoil/models/cert_manager/py.typed
cloudcoil/models/cert_manager/v1.py
cloudcoil/models/cert_manager/acme/__init__.py
cloudcoil/models/cert_manager/acme/v1.py
cloudcoil_models_cert_manager-1.17.1.0.dist-info/METADATA
cloudcoil_models_cert_manager-1.17.1.0.dist-info/WHEEL
cloudcoil_models_cert_manager-1.17.1.0.dist-info/licenses/LICENSE
cloudcoil_models_cert_manager-1.17.1.0.dist-info/RECORD
